Metadata-Version: 2.1
Name: uitnlp
Version: 0.1.2
Summary: UITNLP: A Python NLP Library for Vietnamese
Home-page: https://github.com/uitnlp/uitnlp.git
Author: The UIT Natural Language Processing Group
Author-email: vund@uit.edu.vn
License: Apache License 2.0
Keywords: natural-language-processing nlp natural-language-understanding uit-nlp vietnamese-word-segmentation
Platform: UNKNOWN
Classifier: Topic :: Scientific/Engineering :: Artificial Intelligence
Classifier: Programming Language :: Python :: 3.6
Classifier: Programming Language :: Python :: 3.7
Classifier: Programming Language :: Python :: 3.8
Requires-Python: >=3.6
